bigfun/__init__.py
bigfun/bigfunctions.py
bigfun/cli.py
bigfun/load_table.py
bigfun/utils.py
bigfun/datastore/index.yaml
bigfun/templates/Dockerfile
bigfun/templates/aggregate_function_js.sql
bigfun/templates/aggregate_function_sql.sql
bigfun/templates/aggregate_function_sql_test.sql
bigfun/templates/bigfunction.md
bigfun/templates/bookmarklet.js
bigfun/templates/data.md
bigfun/templates/folder.md
bigfun/templates/function_js.sql
bigfun/templates/function_py.py
bigfun/templates/function_py.sql
bigfun/templates/function_py_test.py
bigfun/templates/function_sql.sql
bigfun/templates/function_sql_test.sql
bigfun/templates/mkdocs.yml
bigfun/templates/procedure.sql
bigfun/templates/procedure_test.sql
bigfun/templates/table_function.sql
bigfunctions-0.36.dist-info/licenses/LICENSE
bigfunctions-0.36.dist-info/METADATA
bigfunctions-0.36.dist-info/WHEEL
bigfunctions-0.36.dist-info/entry_points.txt
bigfunctions-0.36.dist-info/top_level.txt
bigfunctions-0.36.dist-info/RECORD
