Metadata-Version: 2.4
Name: bigfunctions
Version: 0.36
Summary: Supercharge BigQuery with BigFunctions
Author-email: Unytics <paul.marcombes@unytics.io>
License: MIT
Project-URL: Homepage, https://unytics.io/bigfunctions/
Project-URL: Documentation, https://unytics.io/bigfunctions/framework/
Project-URL: GitHub, https://github.com/unytics/bigfunctions
Keywords: bigquery,data,analytics
Classifier: Programming Language :: Python :: 3
Classifier: Operating System :: OS Independent
Requires-Python: >=3.10
License-File: LICENSE
Requires-Dist: google-cloud-bigquery
Requires-Dist: google-cloud-bigquery-connection
Requires-Dist: google-cloud-storage
Requires-Dist: pyyaml
Requires-Dist: jinja2
Requires-Dist: mkdocs-material
Requires-Dist: mkdocs-awesome-nav
Requires-Dist: click
Requires-Dist: click-help-colors
Requires-Dist: cryptography
Requires-Dist: uv
Requires-Dist: google-genai
Provides-Extra: dev
Requires-Dist: pre-commit<4,>=3; extra == "dev"
Dynamic: license-file
